setup.py
diskwarmer/__init__.py
diskwarmer/vmtouchparser.py
diskwarmer.egg-info/PKG-INFO
diskwarmer.egg-info/SOURCES.txt
diskwarmer.egg-info/dependency_links.txt
diskwarmer.egg-info/entry_points.txt
diskwarmer.egg-info/not-zip-safe
diskwarmer.egg-info/requires.txt
diskwarmer.egg-info/top_level.txt