Metadata-Version: 1.0
Name: diskwarmer
Version: 0.0.1
Summary: tool to help warm disk caches by targeting files which were memory resident in vmtouch reports
Home-page: http://github.com/andrewguy9/diskwarmer
Author: andrew thomson
Author-email: athomsonguy@gmail.com
License: MIT
Platform: UNKNOWN
